{"title":"Combined feed","url":"https://factcheckr.github.io/ted/all.xml","elements":[{"title":"undefined (TED Talks 한국어)","contents":"TED-Ed","retrieved":1686032561118},{"title":"undefined (TED Talks 한국어)","contents":"David Biello","retrieved":1686032561118},{"title":"undefined (TED Talks 한국어)","contents":"Golshifteh Farahani","retrieved":1686032561119},{"title":"undefined (TED Talks 한국어)","contents":"Stephanie Honchell Smith","retrieved":1686032561119},{"title":"undefined (TED Talks 한국어)","contents":"G. Richard Scott","retrieved":1686032561119},{"title":"undefined (TED Talks 한국어)","contents":"Audra A. Diptée","retrieved":1686032561120},{"title":"undefined (TED Talks 한국어)","contents":"Nigel Rothfels","retrieved":1686032561125},{"title":"undefined (TED Talks 한국어)","contents":"Andrew Smith","retrieved":1686032561132},{"title":"undefined (TED Talks 한국어)","contents":"Stephanie Honchell Smith","retrieved":1686032561136},{"title":"undefined (TED Talks 한국어)","contents":"Dave Sivaprasad","retrieved":1686032561136},{"title":"undefined (TED Talks 한국어)","contents":"Kenneth Chabert","retrieved":1686032561136},{"title":"undefined (TED Talks 한국어)","contents":"Chinyanta Kabaso","retrieved":1686032561139},{"title":"undefined (TED Talks 한국어)","contents":"Tsedal Neeley","retrieved":1686032561142},{"title":"undefined (TED Talks 한국어)","contents":"Sydney Iaukea","retrieved":1686032561143},{"title":"undefined (TED Talks 한국어)","contents":"Susan Freitas and Darren Parker","retrieved":1686032561145},{"title":"undefined (TED Talks 한국어)","contents":"Malachy McHugh","retrieved":1686032561147},{"title":"undefined (TED Talks 한국어)","contents":"Dan Finkel","retrieved":1686032561149},{"title":"undefined (TED Talks 한국어)","contents":"Charles Wallace","retrieved":1686032561150},{"title":"undefined (TED Talks 한국어)","contents":"Wendy Suzuki","retrieved":1686032561152},{"title":"undefined (TED Talks 한국어)","contents":"Birte Kristiansen and Petra Sijpesteijn","retrieved":1686032561154},{"title":"undefined (TED Talks 한국어)","contents":"Emily Grubert","retrieved":1686032561156},{"title":"undefined (TED Talks 한국어)","contents":"Antonio Cataldo","retrieved":1686032561159},{"title":"undefined (TED Talks 한국어)","contents":"Nedra Glover Tawwab","retrieved":1686032561161},{"title":"undefined (TED Talks 한국어)","contents":"TED-Ed","retrieved":1686032561162},{"title":"undefined (TED Talks 한국어)","contents":"Phnam Bagley","retrieved":1686032561167},{"title":"undefined (TED Talks 한국어)","contents":"Kris Alexander","retrieved":1686032561168},{"title":"undefined (TED Talks 한국어)","contents":"Rebekah Shirley","retrieved":1686032561169},{"title":"undefined (TED Talks 한국어)","contents":"Michael Middlebrooks","retrieved":1686032561171},{"title":"undefined (TED Talks 한국어)","contents":"Jean-Baptiste P. Koehl","retrieved":1686032561174},{"title":"undefined (TED Talks 한국어)","contents":"TED-Ed","retrieved":1686032561175},{"title":"undefined (TED Talks 한국어)","contents":"Saad Bhamla","retrieved":1686032561178},{"title":"undefined (TED Talks 한국어)","contents":"Brendan Rogers and Jessica Howard","retrieved":1686032561180},{"title":"undefined (TED Talks 한국어)","contents":"Tessa Clarke","retrieved":1686032561182},{"title":"undefined (TED Talks 한국어)","contents":"Mollie Godfrey","retrieved":1686032561185},{"title":"undefined (TED Talks 한국어)","contents":"Jan Wurzbacher","retrieved":1686032561187},{"title":"undefined (TED Talks 한국어)","contents":"TED-Ed","retrieved":1686032561188}]}