{"title":"Combined feed","url":"https://factcheckr.github.io/ted/all.xml","elements":[{"title":"undefined (TED Talks 한국어)","contents":"Henry Richardson","retrieved":1665843922282},{"title":"undefined (TED Talks 한국어)","contents":"Jen Gunter","retrieved":1665843922284},{"title":"undefined (TED Talks 한국어)","contents":"TED-Ed","retrieved":1665843922286},{"title":"undefined (TED Talks 한국어)","contents":"Iseult Gillespie","retrieved":1665843922287},{"title":"undefined (TED Talks 한국어)","contents":"Albert Fox Cahn","retrieved":1665843922288},{"title":"undefined (TED Talks 한국어)","contents":"Elizabeth Cox","retrieved":1665843922289},{"title":"undefined (TED Talks 한국어)","contents":"TED-Ed","retrieved":1665843922289},{"title":"undefined (TED Talks 한국어)","contents":"Barbara Thorne","retrieved":1665843922290},{"title":"undefined (TED Talks 한국어)","contents":"Fabio Pacucci","retrieved":1665843922291},{"title":"undefined (TED Talks 한국어)","contents":"Micaela Mantegna","retrieved":1665843922292},{"title":"undefined (TED Talks 한국어)","contents":"Ilan Stavans","retrieved":1665843922293},{"title":"undefined (TED Talks 한국어)","contents":"Charles Wallace and Sajan Saini","retrieved":1665843922294},{"title":"undefined (TED Talks 한국어)","contents":"Dan Widmaier","retrieved":1665843922295},{"title":"undefined (TED Talks 한국어)","contents":"Lyla Latif","retrieved":1665843922297},{"title":"undefined (TED Talks 한국어)","contents":"Parag Khanna","retrieved":1665843922300},{"title":"undefined (TED Talks 한국어)","contents":"Zahra Biabani","retrieved":1665843922301},{"title":"undefined (TED Talks 한국어)","contents":"Chanda Prescod-Weinstein","retrieved":1665843922308},{"title":"undefined (TED Talks 한국어)","contents":"Tierney Thys and Christian Sardet","retrieved":1665843922309},{"title":"undefined (TED Talks 한국어)","contents":"Thomas Heatherwick","retrieved":1665843922312},{"title":"undefined (TED Talks 한국어)","contents":"Olga Kitaina","retrieved":1665843922316},{"title":"undefined (TED Talks 한국어)","contents":"Judy Grisel","retrieved":1665843922320},{"title":"undefined (TED Talks 한국어)","contents":"TED-Ed","retrieved":1665843922321},{"title":"undefined (TED Talks 한국어)","contents":"Andrew Lovering","retrieved":1665843922323},{"title":"undefined (TED Talks 한국어)","contents":"JR","retrieved":1665843922324},{"title":"undefined (TED Talks 한국어)","contents":"Grace Smith-Viduarre and Tim Wright","retrieved":1665843922325},{"title":"undefined (TED Talks 한국어)","contents":"Jennifer Heldmann","retrieved":1665843922326},{"title":"undefined (TED Talks 한국어)","contents":"Yuval Noah Harari","retrieved":1665843922328},{"title":"undefined (TED Talks 한국어)","contents":"Luka Seamus Wright","retrieved":1665843922329},{"title":"undefined (TED Talks 한국어)","contents":"Victoria Hwang","retrieved":1665843922330},{"title":"undefined (TED Talks 한국어)","contents":"James Hodge","retrieved":1665843922333},{"title":"undefined (TED Talks 한국어)","contents":"Elizabeth Cox","retrieved":1665843922334},{"title":"undefined (TED Talks 한국어)","contents":"Craig Richard","retrieved":1665843922336},{"title":"undefined (TED Talks 한국어)","contents":"Bryce Dallas Howard","retrieved":1665843922350},{"title":"undefined (TED Talks 한국어)","contents":"Agnes Larsson","retrieved":1665843922351},{"title":"undefined (TED Talks 한국어)","contents":"Sarah Stroud","retrieved":1665843922352},{"title":"undefined (TED Talks 한국어)","contents":"Bruce Feiler","retrieved":1665843922352}]}