{"title":"Combined feed","url":"https://factcheckr.github.io/ted/all.xml","elements":[{"title":"undefined (TED Talks 한국어)","contents":"Luka Seamus Wright","retrieved":1656693359967},{"title":"undefined (TED Talks 한국어)","contents":"Victoria Hwang","retrieved":1656693359967},{"title":"undefined (TED Talks 한국어)","contents":"Agnes Larsson","retrieved":1656693359968},{"title":"undefined (TED Talks 한국어)","contents":"Sarah Stroud","retrieved":1656693359970},{"title":"undefined (TED Talks 한국어)","contents":"Timothy Williams","retrieved":1656693359971},{"title":"undefined (TED Talks 한국어)","contents":"Marvin Rees","retrieved":1656693359972},{"title":"undefined (TED Talks 한국어)","contents":"Roni Shanoada","retrieved":1656693359973},{"title":"undefined (TED Talks 한국어)","contents":"Anees Bahji","retrieved":1656693359974},{"title":"undefined (TED Talks 한국어)","contents":"Dorie Clark","retrieved":1656693359975},{"title":"undefined (TED Talks 한국어)","contents":"Diana Sierra Becerra","retrieved":1656693359977},{"title":"undefined (TED Talks 한국어)","contents":"Bektour Iskender","retrieved":1656693359980},{"title":"undefined (TED Talks 한국어)","contents":"Jonathan Smith","retrieved":1656693359980},{"title":"undefined (TED Talks 한국어)","contents":"Kayla Wolf","retrieved":1656693359983},{"title":"undefined (TED Talks 한국어)","contents":"Celina de Sola","retrieved":1656693359984},{"title":"undefined (TED Talks 한국어)","contents":"Sue Natali","retrieved":1656693359987},{"title":"undefined (TED Talks 한국어)","contents":"Lucia Carminati","retrieved":1656693359988},{"title":"undefined (TED Talks 한국어)","contents":"Shannon Zhao","retrieved":1656693359990},{"title":"undefined (TED Talks 한국어)","contents":"Henri Picciotto","retrieved":1656693359991},{"title":"undefined (TED Talks 한국어)","contents":"John C. Mather","retrieved":1656693359995},{"title":"undefined (TED Talks 한국어)","contents":"Bill Gates","retrieved":1656693359995},{"title":"undefined (TED Talks 한국어)","contents":"Christopher M. Moreman","retrieved":1656693359997},{"title":"undefined (TED Talks 한국어)","contents":"Nat Keohane","retrieved":1656693359998},{"title":"undefined (TED Talks 한국어)","contents":"Allyson Felix","retrieved":1656693360000},{"title":"undefined (TED Talks 한국어)","contents":"Ameya Gondhalekar","retrieved":1656693360001},{"title":"undefined (TED Talks 한국어)","contents":"Iseult Gillespie","retrieved":1656693360003},{"title":"undefined (TED Talks 한국어)","contents":"Zoya Lytvyn","retrieved":1656693360004},{"title":"undefined (TED Talks 한국어)","contents":"Alex Worsnip","retrieved":1656693360006},{"title":"undefined (TED Talks 한국어)","contents":"Garry Kasparov","retrieved":1656693360008},{"title":"undefined (TED Talks 한국어)","contents":"Andrew Whitworth","retrieved":1656693360009},{"title":"undefined (TED Talks 한국어)","contents":"Gabriel Kra","retrieved":1656693360011},{"title":"undefined (TED Talks 한국어)","contents":"Stephanie Honchell Smith","retrieved":1656693360012},{"title":"undefined (TED Talks 한국어)","contents":"Jarrett J. Krosoczka","retrieved":1656693360014},{"title":"undefined (TED Talks 한국어)","contents":"Fabio Pacucci","retrieved":1656693360015},{"title":"undefined (TED Talks 한국어)","contents":"Hyeonmi Kim","retrieved":1656693360017},{"title":"undefined (TED Talks 한국어)","contents":"Henri Picciotto","retrieved":1656693360019},{"title":"undefined (TED Talks 한국어)","contents":"Fariel Salahuddin","retrieved":1656693360020}]}