{"title":"Combined feed","url":"https://factcheckr.github.io/ted/all.xml","elements":[{"title":"undefined (TED Talks 한국어)","contents":"Sheryl Lee Ralph","retrieved":1688361569449},{"title":"undefined (TED Talks 한국어)","contents":"Iseult Gillespie","retrieved":1688361569449},{"title":"undefined (TED Talks 한국어)","contents":"Susan G. Wardle","retrieved":1688361569449},{"title":"undefined (TED Talks 한국어)","contents":"Carolyn Beans","retrieved":1688361569449},{"title":"undefined (TED Talks 한국어)","contents":"Ali Hajimiri","retrieved":1688361569449},{"title":"undefined (TED Talks 한국어)","contents":"Sascha Morrell","retrieved":1688361569450},{"title":"undefined (TED Talks 한국어)","contents":"Dan Finkel","retrieved":1688361569450},{"title":"undefined (TED Talks 한국어)","contents":"Sixto Cancel","retrieved":1688361569450},{"title":"undefined (TED Talks 한국어)","contents":"George Zaidan","retrieved":1688361569450},{"title":"undefined (TED Talks 한국어)","contents":"TED-Ed","retrieved":1688361569459},{"title":"undefined (TED Talks 한국어)","contents":"Cecilia M. Orphan","retrieved":1688361569468},{"title":"undefined (TED Talks 한국어)","contents":"David Biello","retrieved":1688361569468},{"title":"undefined (TED Talks 한국어)","contents":"Sheena Meade","retrieved":1688361569468},{"title":"undefined (TED Talks 한국어)","contents":"Golshifteh Farahani","retrieved":1688361569469},{"title":"undefined (TED Talks 한국어)","contents":"Stephanie Honchell Smith","retrieved":1688361569469},{"title":"undefined (TED Talks 한국어)","contents":"G. Richard Scott","retrieved":1688361569470},{"title":"undefined (TED Talks 한국어)","contents":"Audra A. Diptée","retrieved":1688361569470},{"title":"undefined (TED Talks 한국어)","contents":"Nigel Rothfels","retrieved":1688361569472},{"title":"undefined (TED Talks 한국어)","contents":"Jiaying Zhao","retrieved":1688361569474},{"title":"undefined (TED Talks 한국어)","contents":"Andrew Smith","retrieved":1688361569476},{"title":"undefined (TED Talks 한국어)","contents":"Stephanie Honchell Smith","retrieved":1688361569477},{"title":"undefined (TED Talks 한국어)","contents":"Dave Sivaprasad","retrieved":1688361569479},{"title":"undefined (TED Talks 한국어)","contents":"Kenneth Chabert","retrieved":1688361569481},{"title":"undefined (TED Talks 한국어)","contents":"Kathryn M. Stephenson and David L. Suskind","retrieved":1688361569483},{"title":"undefined (TED Talks 한국어)","contents":"Chinyanta Kabaso","retrieved":1688361569484},{"title":"undefined (TED Talks 한국어)","contents":"Tsedal Neeley","retrieved":1688361569489},{"title":"undefined (TED Talks 한국어)","contents":"Sydney Iaukea","retrieved":1688361569491},{"title":"undefined (TED Talks 한국어)","contents":"Alysa McCall","retrieved":1688361569492},{"title":"undefined (TED Talks 한국어)","contents":"Susan Freitas and Darren Parker","retrieved":1688361569494},{"title":"undefined (TED Talks 한국어)","contents":"TED-Ed","retrieved":1688361569496},{"title":"undefined (TED Talks 한국어)","contents":"Megan Alubicki Flick","retrieved":1688361569498},{"title":"undefined (TED Talks 한국어)","contents":"Malachy McHugh","retrieved":1688361569500},{"title":"undefined (TED Talks 한국어)","contents":"Dan Finkel","retrieved":1688361569503},{"title":"undefined (TED Talks 한국어)","contents":"Charles Wallace","retrieved":1688361569505},{"title":"undefined (TED Talks 한국어)","contents":"Wendy Suzuki","retrieved":1688361569506},{"title":"undefined (TED Talks 한국어)","contents":"Birte Kristiansen and Petra Sijpesteijn","retrieved":1688361569508}]}