{"title":"Combined feed","url":"https://factcheckr.github.io/ted/all.xml","elements":[{"title":"undefined (TED Talks 한국어)","contents":"TED-Ed","retrieved":1685712232083},{"title":"undefined (TED Talks 한국어)","contents":"David Biello","retrieved":1685712232084},{"title":"undefined (TED Talks 한국어)","contents":"Golshifteh Farahani","retrieved":1685712232084},{"title":"undefined (TED Talks 한국어)","contents":"Stephanie Honchell Smith","retrieved":1685712232092},{"title":"undefined (TED Talks 한국어)","contents":"G. Richard Scott","retrieved":1685712232092},{"title":"undefined (TED Talks 한국어)","contents":"Audra A. Diptée","retrieved":1685712232093},{"title":"undefined (TED Talks 한국어)","contents":"Nigel Rothfels","retrieved":1685712232095},{"title":"undefined (TED Talks 한국어)","contents":"Andrew Smith","retrieved":1685712232097},{"title":"undefined (TED Talks 한국어)","contents":"Stephanie Honchell Smith","retrieved":1685712232098},{"title":"undefined (TED Talks 한국어)","contents":"Dave Sivaprasad","retrieved":1685712232100},{"title":"undefined (TED Talks 한국어)","contents":"Kenneth Chabert","retrieved":1685712232102},{"title":"undefined (TED Talks 한국어)","contents":"Chinyanta Kabaso","retrieved":1685712232104},{"title":"undefined (TED Talks 한국어)","contents":"Tsedal Neeley","retrieved":1685712232105},{"title":"undefined (TED Talks 한국어)","contents":"Sydney Iaukea","retrieved":1685712232106},{"title":"undefined (TED Talks 한국어)","contents":"Susan Freitas and Darren Parker","retrieved":1685712232107},{"title":"undefined (TED Talks 한국어)","contents":"Malachy McHugh","retrieved":1685712232107},{"title":"undefined (TED Talks 한국어)","contents":"Dan Finkel","retrieved":1685712232108},{"title":"undefined (TED Talks 한국어)","contents":"Charles Wallace","retrieved":1685712232109},{"title":"undefined (TED Talks 한국어)","contents":"Wendy Suzuki","retrieved":1685712232110},{"title":"undefined (TED Talks 한국어)","contents":"Birte Kristiansen and Petra Sijpesteijn","retrieved":1685712232111},{"title":"undefined (TED Talks 한국어)","contents":"Emily Grubert","retrieved":1685712232112},{"title":"undefined (TED Talks 한국어)","contents":"Antonio Cataldo","retrieved":1685712232113},{"title":"undefined (TED Talks 한국어)","contents":"Nedra Glover Tawwab","retrieved":1685712232117},{"title":"undefined (TED Talks 한국어)","contents":"TED-Ed","retrieved":1685712232119},{"title":"undefined (TED Talks 한국어)","contents":"Phnam Bagley","retrieved":1685712232121},{"title":"undefined (TED Talks 한국어)","contents":"Rebekah Shirley","retrieved":1685712232127},{"title":"undefined (TED Talks 한국어)","contents":"Michael Middlebrooks","retrieved":1685712232135},{"title":"undefined (TED Talks 한국어)","contents":"Jean-Baptiste P. Koehl","retrieved":1685712232136},{"title":"undefined (TED Talks 한국어)","contents":"TED-Ed","retrieved":1685712232136},{"title":"undefined (TED Talks 한국어)","contents":"Brendan Rogers and Jessica Howard","retrieved":1685712232137},{"title":"undefined (TED Talks 한국어)","contents":"Tessa Clarke","retrieved":1685712232138},{"title":"undefined (TED Talks 한국어)","contents":"Mollie Godfrey","retrieved":1685712232140},{"title":"undefined (TED Talks 한국어)","contents":"Jan Wurzbacher","retrieved":1685712232143},{"title":"undefined (TED Talks 한국어)","contents":"TED-Ed","retrieved":1685712232146},{"title":"undefined (TED Talks 한국어)","contents":"Shannon N. Tessier","retrieved":1685712232148},{"title":"undefined (TED Talks 한국어)","contents":"Ksenia Petrichenko","retrieved":1685712232151}]}