{"title":"Combined feed","url":"https://factcheckr.github.io/ted/all.xml","elements":[{"title":"undefined (TED Talks 한국어)","contents":"TED-Ed","retrieved":1685805395220},{"title":"undefined (TED Talks 한국어)","contents":"David Biello","retrieved":1685805395220},{"title":"undefined (TED Talks 한국어)","contents":"Golshifteh Farahani","retrieved":1685805395220},{"title":"undefined (TED Talks 한국어)","contents":"Stephanie Honchell Smith","retrieved":1685805395220},{"title":"undefined (TED Talks 한국어)","contents":"G. Richard Scott","retrieved":1685805395220},{"title":"undefined (TED Talks 한국어)","contents":"Audra A. Diptée","retrieved":1685805395220},{"title":"undefined (TED Talks 한국어)","contents":"Nigel Rothfels","retrieved":1685805395220},{"title":"undefined (TED Talks 한국어)","contents":"Andrew Smith","retrieved":1685805395220},{"title":"undefined (TED Talks 한국어)","contents":"Stephanie Honchell Smith","retrieved":1685805395223},{"title":"undefined (TED Talks 한국어)","contents":"Dave Sivaprasad","retrieved":1685805395223},{"title":"undefined (TED Talks 한국어)","contents":"Kenneth Chabert","retrieved":1685805395223},{"title":"undefined (TED Talks 한국어)","contents":"Chinyanta Kabaso","retrieved":1685805395223},{"title":"undefined (TED Talks 한국어)","contents":"Tsedal Neeley","retrieved":1685805395229},{"title":"undefined (TED Talks 한국어)","contents":"Sydney Iaukea","retrieved":1685805395229},{"title":"undefined (TED Talks 한국어)","contents":"Susan Freitas and Darren Parker","retrieved":1685805395229},{"title":"undefined (TED Talks 한국어)","contents":"Malachy McHugh","retrieved":1685805395229},{"title":"undefined (TED Talks 한국어)","contents":"Dan Finkel","retrieved":1685805395229},{"title":"undefined (TED Talks 한국어)","contents":"Charles Wallace","retrieved":1685805395229},{"title":"undefined (TED Talks 한국어)","contents":"Wendy Suzuki","retrieved":1685805395229},{"title":"undefined (TED Talks 한국어)","contents":"Birte Kristiansen and Petra Sijpesteijn","retrieved":1685805395231},{"title":"undefined (TED Talks 한국어)","contents":"Emily Grubert","retrieved":1685805395231},{"title":"undefined (TED Talks 한국어)","contents":"Antonio Cataldo","retrieved":1685805395231},{"title":"undefined (TED Talks 한국어)","contents":"Nedra Glover Tawwab","retrieved":1685805395234},{"title":"undefined (TED Talks 한국어)","contents":"TED-Ed","retrieved":1685805395239},{"title":"undefined (TED Talks 한국어)","contents":"Phnam Bagley","retrieved":1685805395240},{"title":"undefined (TED Talks 한국어)","contents":"Kris Alexander","retrieved":1685805395240},{"title":"undefined (TED Talks 한국어)","contents":"Rebekah Shirley","retrieved":1685805395241},{"title":"undefined (TED Talks 한국어)","contents":"Michael Middlebrooks","retrieved":1685805395243},{"title":"undefined (TED Talks 한국어)","contents":"Jean-Baptiste P. Koehl","retrieved":1685805395244},{"title":"undefined (TED Talks 한국어)","contents":"TED-Ed","retrieved":1685805395246},{"title":"undefined (TED Talks 한국어)","contents":"Brendan Rogers and Jessica Howard","retrieved":1685805395248},{"title":"undefined (TED Talks 한국어)","contents":"Tessa Clarke","retrieved":1685805395250},{"title":"undefined (TED Talks 한국어)","contents":"Mollie Godfrey","retrieved":1685805395252},{"title":"undefined (TED Talks 한국어)","contents":"Jan Wurzbacher","retrieved":1685805395254},{"title":"undefined (TED Talks 한국어)","contents":"TED-Ed","retrieved":1685805395256},{"title":"undefined (TED Talks 한국어)","contents":"Shannon N. Tessier","retrieved":1685805395258}]}