{"title":"TED Talks 한국어","url":"https://www.ted.com/talks?sort=newest&language=ko","favicon":"https://pa.tedcdn.com/favicon.ico","elements":[{"contents":"TED-Ed","retrieved":1675142298088},{"contents":"Shannon Odell","retrieved":1675142298095},{"contents":"Clementine Jacoby","retrieved":1675142298095},{"contents":"Miles Zhang","retrieved":1675142298096},{"contents":"Frank Cogliano","retrieved":1675142298110},{"contents":"Jessie Christiansen","retrieved":1675142298110},{"contents":"Colin Averill","retrieved":1675142298110},{"contents":"Glynnis Hood","retrieved":1675142298110},{"contents":"Joshua Paul Dale","retrieved":1675142298110},{"contents":"Shannon Odell","retrieved":1675142298113},{"contents":"TED-Ed","retrieved":1675142298113},{"contents":"Xavier Cortada","retrieved":1675142298118},{"contents":"Gautam Shah","retrieved":1675142298119},{"contents":"Shannon Odell","retrieved":1675142298120},{"contents":"TED-Ed","retrieved":1675142298121},{"contents":"TED-Ed","retrieved":1675142298122},{"contents":"TED-Ed","retrieved":1675142298123},{"contents":"TED-Ed","retrieved":1675142298124},{"contents":"Ralph Chami","retrieved":1675142298129},{"contents":"Rob Ulrich","retrieved":1675142298131},{"contents":"TED-Ed","retrieved":1675142298132},{"contents":"Rebecca L. Walker","retrieved":1675142298135},{"contents":"Robert Katzschmann","retrieved":1675142298143},{"contents":"TED-Ed","retrieved":1675142298145},{"contents":"Jen Gunter","retrieved":1675142298146},{"contents":"TED-Ed","retrieved":1675142298148},{"contents":"Jason W. Chin","retrieved":1675142298150},{"contents":"Will Guidara","retrieved":1675142298151},{"contents":"Emmanuel During","retrieved":1675142298152},{"contents":"Shreya Joshi","retrieved":1675142298154},{"contents":"Chris Roe","retrieved":1675142298155},{"contents":"TED-Ed","retrieved":1675142298156},{"contents":"Shannon Odell","retrieved":1675142298158},{"contents":"Riley Moynes","retrieved":1675142298159},{"contents":"Soraya Field Fiorio","retrieved":1675142298161},{"contents":"Jen Gunter","retrieved":1675142298162}]}