{"title":"TED Talks 한국어","url":"https://www.ted.com/talks?sort=newest&language=ko","favicon":"https://pa.tedcdn.com/favicon.ico","elements":[{"contents":"Mariela Pajuelo and Javier Antonio Quinones","retrieved":1694888380392},{"contents":"Kenny Coogan","retrieved":1694888380392},{"contents":"Refik Anadol","retrieved":1694888380392},{"contents":"Carolyn Beans","retrieved":1694888380392},{"contents":"Albert Zink","retrieved":1694888380393},{"contents":"Barbara F. Walter","retrieved":1694888380393},{"contents":"Fabio Pacucci","retrieved":1694888380395},{"contents":"Lindsay DeMarchi","retrieved":1694888380395},{"contents":"George Zaidan","retrieved":1694888380395},{"contents":"Beatrice K. Otto","retrieved":1694888380395},{"contents":"Andrew Leland","retrieved":1694888380395},{"contents":"Coleman Hughes","retrieved":1694888380395},{"contents":"TED-Ed","retrieved":1694888380396},{"contents":"Garry Cooper","retrieved":1694888380397},{"contents":"Stephanie Honchell Smith","retrieved":1694888380398},{"contents":"Anneliese Mehnert","retrieved":1694888380399},{"contents":"Shannon Odell","retrieved":1694888380400},{"contents":"Barbara J. King","retrieved":1694888380401},{"contents":"Eliezer Yudkowsky","retrieved":1694888380402},{"contents":"Daniel Finkel","retrieved":1694888380403},{"contents":"Shane Campbell-Staton","retrieved":1694888380404},{"contents":"Susanne Buckley-Zistel","retrieved":1694888380405},{"contents":"Conor Russomanno","retrieved":1694888380407},{"contents":"Shannon Odell","retrieved":1694888380408},{"contents":"Angus Hervey","retrieved":1694888380409},{"contents":"Sheryl Lee Ralph","retrieved":1694888380410},{"contents":"Carolyn Harris","retrieved":1694888380411},{"contents":"Richard Reeves","retrieved":1694888380412},{"contents":"Iseult Gillespie","retrieved":1694888380413},{"contents":"Ian Bremmer","retrieved":1694888380416},{"contents":"Susan G. Wardle","retrieved":1694888380416},{"contents":"Mark Edwards","retrieved":1694888380425},{"contents":"Sally Frampton","retrieved":1694888380426},{"contents":"Carolyn Beans","retrieved":1694888380427},{"contents":"Ali Hajimiri","retrieved":1694888380428},{"contents":"Hanako Sawada","retrieved":1694888380429}]}