{"title":"TED Talks 한국어","url":"https://www.ted.com/talks?sort=newest&language=ko","favicon":"https://pa.tedcdn.com/favicon.ico","elements":[{"contents":"David Biello","retrieved":1685298038985},{"contents":"Golshifteh Farahani","retrieved":1685298038985},{"contents":"Stephanie Honchell Smith","retrieved":1685298038985},{"contents":"G. Richard Scott","retrieved":1685298038985},{"contents":"Audra A. Diptée","retrieved":1685298038989},{"contents":"Nigel Rothfels","retrieved":1685298038989},{"contents":"Andrew Smith","retrieved":1685298038989},{"contents":"Stephanie Honchell Smith","retrieved":1685298038989},{"contents":"Dave Sivaprasad","retrieved":1685298038989},{"contents":"Chinyanta Kabaso","retrieved":1685298038989},{"contents":"Tsedal Neeley","retrieved":1685298038989},{"contents":"Sydney Iaukea","retrieved":1685298038989},{"contents":"Susan Freitas and Darren Parker","retrieved":1685298038989},{"contents":"Malachy McHugh","retrieved":1685298038989},{"contents":"Dan Finkel","retrieved":1685298038989},{"contents":"Charles Wallace","retrieved":1685298038989},{"contents":"Wendy Suzuki","retrieved":1685298038989},{"contents":"Birte Kristiansen and Petra Sijpesteijn","retrieved":1685298038992},{"contents":"Emily Grubert","retrieved":1685298039000},{"contents":"Antonio Cataldo","retrieved":1685298039001},{"contents":"TED-Ed","retrieved":1685298039003},{"contents":"Phnam Bagley","retrieved":1685298039003},{"contents":"Rebekah Shirley","retrieved":1685298039003},{"contents":"Michael Middlebrooks","retrieved":1685298039003},{"contents":"Jean-Baptiste P. Koehl","retrieved":1685298039004},{"contents":"TED-Ed","retrieved":1685298039005},{"contents":"Brendan Rogers and Jessica Howard","retrieved":1685298039011},{"contents":"Mollie Godfrey","retrieved":1685298039011},{"contents":"Jan Wurzbacher","retrieved":1685298039011},{"contents":"TED-Ed","retrieved":1685298039011},{"contents":"Shannon N. Tessier","retrieved":1685298039017},{"contents":"Ksenia Petrichenko","retrieved":1685298039017},{"contents":"Raymond Adkins","retrieved":1685298039017},{"contents":"Keenan Norris","retrieved":1685298039017},{"contents":"Tolu Oyekan","retrieved":1685298039020},{"contents":"Jawad Sharif","retrieved":1685298039021}]}