{"title":"TED Talks 한국어","url":"https://www.ted.com/talks?sort=newest&language=ko","favicon":"https://pa.tedcdn.com/favicon.ico","elements":[{"contents":"TED-Ed","retrieved":1691371786074},{"contents":"Anneliese Mehnert","retrieved":1691371786076},{"contents":"Shannon Odell","retrieved":1691371786078},{"contents":"Barbara J. King","retrieved":1691371786080},{"contents":"Daniel Finkel","retrieved":1691371786082},{"contents":"Susanne Buckley-Zistel","retrieved":1691371786084},{"contents":"Angus Hervey","retrieved":1691371786086},{"contents":"Sheryl Lee Ralph","retrieved":1691371786088},{"contents":"Carolyn Harris","retrieved":1691371786090},{"contents":"Iseult Gillespie","retrieved":1691371786092},{"contents":"Ian Bremmer","retrieved":1691371786094},{"contents":"Susan G. Wardle","retrieved":1691371786096},{"contents":"Mark Edwards","retrieved":1691371786098},{"contents":"Sally Frampton","retrieved":1691371786099},{"contents":"Carolyn Beans","retrieved":1691371786101},{"contents":"Ali Hajimiri","retrieved":1691371786109},{"contents":"Hanako Sawada","retrieved":1691371786113},{"contents":"Sascha Morrell","retrieved":1691371786114},{"contents":"Dan Finkel","retrieved":1691371786116},{"contents":"Normand Voyer","retrieved":1691371786119},{"contents":"Sixto Cancel","retrieved":1691371786120},{"contents":"George Zaidan","retrieved":1691371786122},{"contents":"TED-Ed","retrieved":1691371786125},{"contents":"Cecilia M. Orphan","retrieved":1691371786126},{"contents":"Andy Dunn","retrieved":1691371786128},{"contents":"David Biello","retrieved":1691371786132},{"contents":"Keyu Jin","retrieved":1691371786135},{"contents":"Joëlle Rollo-Koster","retrieved":1691371786137},{"contents":"Azim Shariff","retrieved":1691371786138},{"contents":"Sheena Meade","retrieved":1691371786140},{"contents":"Golshifteh Farahani","retrieved":1691371786144},{"contents":"Stephanie Honchell Smith","retrieved":1691371786146},{"contents":"G. Richard Scott","retrieved":1691371786148},{"contents":"Audra A. Diptée","retrieved":1691371786150},{"contents":"Nigel Rothfels","retrieved":1691371786152},{"contents":"Damon Gameau","retrieved":1691371786154}]}