{"title":"TED Talks 한국어","url":"https://www.ted.com/talks?sort=newest&language=ko","favicon":"https://pa.tedcdn.com/favicon.ico","elements":[{"contents":"Clementine Jacoby","retrieved":1674530458844},{"contents":"Frank Cogliano","retrieved":1674530458844},{"contents":"Jessie Christiansen","retrieved":1674530458845},{"contents":"Glynnis Hood","retrieved":1674530458845},{"contents":"Joshua Paul Dale","retrieved":1674530458851},{"contents":"Shannon Odell","retrieved":1674530458851},{"contents":"TED-Ed","retrieved":1674530458851},{"contents":"Xavier Cortada","retrieved":1674530458852},{"contents":"Gautam Shah","retrieved":1674530458852},{"contents":"Shannon Odell","retrieved":1674530458853},{"contents":"TED-Ed","retrieved":1674530458855},{"contents":"TED-Ed","retrieved":1674530458856},{"contents":"TED-Ed","retrieved":1674530458859},{"contents":"TED-Ed","retrieved":1674530458860},{"contents":"Ralph Chami","retrieved":1674530458864},{"contents":"Rob Ulrich","retrieved":1674530458866},{"contents":"TED-Ed","retrieved":1674530458874},{"contents":"Rebecca L. Walker","retrieved":1674530458876},{"contents":"Robert Katzschmann","retrieved":1674530458877},{"contents":"TED-Ed","retrieved":1674530458878},{"contents":"Jen Gunter","retrieved":1674530458878},{"contents":"TED-Ed","retrieved":1674530458887},{"contents":"Jason W. Chin","retrieved":1674530458888},{"contents":"Will Guidara","retrieved":1674530458889},{"contents":"Emmanuel During","retrieved":1674530458889},{"contents":"Shreya Joshi","retrieved":1674530458894},{"contents":"Chris Roe","retrieved":1674530458895},{"contents":"TED-Ed","retrieved":1674530458896},{"contents":"Shannon Odell","retrieved":1674530458897},{"contents":"Riley Moynes","retrieved":1674530458898},{"contents":"Soraya Field Fiorio","retrieved":1674530458900},{"contents":"Jen Gunter","retrieved":1674530458902},{"contents":"TED-Ed","retrieved":1674530458903},{"contents":"Henry Richardson","retrieved":1674530458905},{"contents":"Jen Gunter","retrieved":1674530458907},{"contents":"TED-Ed","retrieved":1674530458908}]}