{"title":"TED Talks 한국어","url":"https://www.ted.com/talks?sort=newest&language=ko","favicon":"https://pa.tedcdn.com/favicon.ico","elements":[{"contents":"Luka Seamus Wright","retrieved":1655285042817},{"contents":"Victoria Hwang","retrieved":1655285042817},{"contents":"Agnes Larsson","retrieved":1655285042817},{"contents":"Sarah Stroud","retrieved":1655285042823},{"contents":"Timothy Williams","retrieved":1655285042826},{"contents":"Marvin Rees","retrieved":1655285042826},{"contents":"Roni Shanoada","retrieved":1655285042826},{"contents":"Anees Bahji","retrieved":1655285042826},{"contents":"Dorie Clark","retrieved":1655285042826},{"contents":"Diana Sierra Becerra","retrieved":1655285042826},{"contents":"Jonathan Smith","retrieved":1655285042827},{"contents":"Kayla Wolf","retrieved":1655285042827},{"contents":"Celina de Sola","retrieved":1655285042828},{"contents":"Sue Natali","retrieved":1655285042833},{"contents":"Lucia Carminati","retrieved":1655285042835},{"contents":"Shannon Zhao","retrieved":1655285042836},{"contents":"Henri Picciotto","retrieved":1655285042838},{"contents":"John C. Mather","retrieved":1655285042843},{"contents":"Bill Gates","retrieved":1655285042844},{"contents":"Christopher M. Moreman","retrieved":1655285042844},{"contents":"Nat Keohane","retrieved":1655285042847},{"contents":"Allyson Felix","retrieved":1655285042849},{"contents":"Ameya Gondhalekar","retrieved":1655285042850},{"contents":"Iseult Gillespie","retrieved":1655285042852},{"contents":"Zoya Lytvyn","retrieved":1655285042854},{"contents":"Alex Worsnip","retrieved":1655285042856},{"contents":"Garry Kasparov","retrieved":1655285042858},{"contents":"Andrew Whitworth","retrieved":1655285042862},{"contents":"Gabriel Kra","retrieved":1655285042870},{"contents":"Stephanie Honchell Smith","retrieved":1655285042870},{"contents":"Jarrett J. Krosoczka","retrieved":1655285042871},{"contents":"Fabio Pacucci","retrieved":1655285042873},{"contents":"Hyeonmi Kim","retrieved":1655285042875},{"contents":"Henri Picciotto","retrieved":1655285042876},{"contents":"Fariel Salahuddin","retrieved":1655285042878},{"contents":"Vera Songwe","retrieved":1655285042879}]}