{"title":"TED Talks 한국어","url":"https://www.ted.com/talks?sort=newest&language=ko","favicon":"https://pa.tedcdn.com/favicon.ico","elements":[{"contents":"Ilan Stavans","retrieved":1662122772373},{"contents":"Charles Wallace and Sajan Saini","retrieved":1662122772373},{"contents":"Dan Widmaier","retrieved":1662122772373},{"contents":"Lyla Latif","retrieved":1662122772374},{"contents":"Parag Khanna","retrieved":1662122772375},{"contents":"Chanda Prescod-Weinstein","retrieved":1662122772377},{"contents":"Tierney Thys and Christian Sardet","retrieved":1662122772377},{"contents":"Judy Grisel","retrieved":1662122772377},{"contents":"TED-Ed","retrieved":1662122772377},{"contents":"Andrew Lovering","retrieved":1662122772387},{"contents":"JR","retrieved":1662122772387},{"contents":"Grace Smith-Viduarre and Tim Wright","retrieved":1662122772388},{"contents":"Yuval Noah Harari","retrieved":1662122772390},{"contents":"Luka Seamus Wright","retrieved":1662122772391},{"contents":"Victoria Hwang","retrieved":1662122772393},{"contents":"James Hodge","retrieved":1662122772393},{"contents":"Craig Richard","retrieved":1662122772394},{"contents":"Bryce Dallas Howard","retrieved":1662122772398},{"contents":"Agnes Larsson","retrieved":1662122772399},{"contents":"Sarah Stroud","retrieved":1662122772399},{"contents":"Bruce Feiler","retrieved":1662122772400},{"contents":"Tom Oxley","retrieved":1662122772401},{"contents":"Timothy Williams","retrieved":1662122772403},{"contents":"Alexis Nikole Nelson","retrieved":1662122772404},{"contents":"Marvin Rees","retrieved":1662122772406},{"contents":"Roni Shanoada","retrieved":1662122772407},{"contents":"Maria Popova","retrieved":1662122772409},{"contents":"Al Gore","retrieved":1662122772410},{"contents":"Anees Bahji","retrieved":1662122772412},{"contents":"Dorie Clark","retrieved":1662122772414},{"contents":"Diana Sierra Becerra","retrieved":1662122772415},{"contents":"Bektour Iskender","retrieved":1662122772417},{"contents":"Jonathan Smith","retrieved":1662122772418},{"contents":"Kayla Wolf","retrieved":1662122772420},{"contents":"Edith Elliott and Shahed Alam","retrieved":1662122772421},{"contents":"Celina de Sola","retrieved":1662122772423}]}