{"title":"TED Talks 한국어","url":"https://www.ted.com/talks?sort=newest&language=ko","favicon":"https://pa.tedcdn.com/favicon.ico","elements":[{"contents":"Golshifteh Farahani","retrieved":1684365440647},{"contents":"Stephanie Honchell Smith","retrieved":1684365440654},{"contents":"G. Richard Scott","retrieved":1684365440655},{"contents":"Audra A. Diptée","retrieved":1684365440663},{"contents":"Nigel Rothfels","retrieved":1684365440665},{"contents":"Andrew Smith","retrieved":1684365440667},{"contents":"Stephanie Honchell Smith","retrieved":1684365440671},{"contents":"Dave Sivaprasad","retrieved":1684365440672},{"contents":"Chinyanta Kabaso","retrieved":1684365440673},{"contents":"Susan Freitas and Darren Parker","retrieved":1684365440674},{"contents":"Malachy McHugh","retrieved":1684365440676},{"contents":"Dan Finkel","retrieved":1684365440677},{"contents":"Charles Wallace","retrieved":1684365440679},{"contents":"Wendy Suzuki","retrieved":1684365440681},{"contents":"Birte Kristiansen and Petra Sijpesteijn","retrieved":1684365440683},{"contents":"Emily Grubert","retrieved":1684365440685},{"contents":"Antonio Cataldo","retrieved":1684365440686},{"contents":"TED-Ed","retrieved":1684365440688},{"contents":"Phnam Bagley","retrieved":1684365440690},{"contents":"Rebekah Shirley","retrieved":1684365440691},{"contents":"Michael Middlebrooks","retrieved":1684365440693},{"contents":"Jean-Baptiste P. Koehl","retrieved":1684365440694},{"contents":"TED-Ed","retrieved":1684365440696},{"contents":"Brendan Rogers and Jessica Howard","retrieved":1684365440698},{"contents":"Mollie Godfrey","retrieved":1684365440700},{"contents":"Jan Wurzbacher","retrieved":1684365440702},{"contents":"TED-Ed","retrieved":1684365440703},{"contents":"Shannon N. Tessier","retrieved":1684365440706},{"contents":"Ksenia Petrichenko","retrieved":1684365440708},{"contents":"Raymond Adkins","retrieved":1684365440710},{"contents":"Keenan Norris","retrieved":1684365440712},{"contents":"Tolu Oyekan","retrieved":1684365440713},{"contents":"Jawad Sharif","retrieved":1684365440715},{"contents":"David Andrew Quist","retrieved":1684365440718},{"contents":"Karlos Hill and Soraya Field Fiorio","retrieved":1684365440719},{"contents":"Talya Hackett","retrieved":1684365440723}]}