{"title":"TED Talks 한국어","url":"https://www.ted.com/talks?sort=newest&language=ko","favicon":"https://pa.tedcdn.com/favicon.ico","elements":[{"contents":"TED-Ed","retrieved":1669949481847},{"contents":"Rob Ulrich","retrieved":1669949481849},{"contents":"TED-Ed","retrieved":1669949481851},{"contents":"Rebecca L. Walker","retrieved":1669949481853},{"contents":"Robert Katzschmann","retrieved":1669949481855},{"contents":"Emmanuel During","retrieved":1669949481857},{"contents":"Chris Roe","retrieved":1669949481858},{"contents":"Shannon Odell","retrieved":1669949481860},{"contents":"Henry Richardson","retrieved":1669949481862},{"contents":"Jen Gunter","retrieved":1669949481864},{"contents":"Iseult Gillespie","retrieved":1669949481865},{"contents":"Hei Man Chan","retrieved":1669949481867},{"contents":"TED-Ed","retrieved":1669949481868},{"contents":"Isabelle Boemeke","retrieved":1669949481870},{"contents":"Iseult Gillespie","retrieved":1669949481872},{"contents":"Albert Fox Cahn","retrieved":1669949481873},{"contents":"Elizabeth Cox","retrieved":1669949481875},{"contents":"Alex Gendler","retrieved":1669949481877},{"contents":"TED-Ed","retrieved":1669949481878},{"contents":"TED-Ed","retrieved":1669949481881},{"contents":"Heejae Lim","retrieved":1669949481881},{"contents":"Barbara Thorne","retrieved":1669949481887},{"contents":"Fabio Pacucci","retrieved":1669949481888},{"contents":"Micaela Mantegna","retrieved":1669949481891},{"contents":"Jamie Bernthal","retrieved":1669949481892},{"contents":"Nina McNeely","retrieved":1669949481894},{"contents":"TED-Ed","retrieved":1669949481895},{"contents":"Petra Sijpesteijn and Birte Kristiansen","retrieved":1669949481897},{"contents":"Ilan Stavans","retrieved":1669949481898},{"contents":"Charles Wallace and Sajan Saini","retrieved":1669949481900},{"contents":"César Cuauhtémoc García Hernández","retrieved":1669949481902},{"contents":"Dan Widmaier","retrieved":1669949481906},{"contents":"Lyla Latif","retrieved":1669949481907},{"contents":"TED-Ed","retrieved":1669949481909},{"contents":"Parag Khanna","retrieved":1669949481911},{"contents":"Zahra Biabani","retrieved":1669949481912}]}